apidisplaypurposes/__init__.py
apidisplaypurposes/displaypurposes.py
api_display_purposes-0.0.3.dist-info/LICENSE
api_display_purposes-0.0.3.dist-info/METADATA
api_display_purposes-0.0.3.dist-info/WHEEL
api_display_purposes-0.0.3.dist-info/top_level.txt
api_display_purposes-0.0.3.dist-info/RECORD
