Metadata-Version: 2.1
Name: api-display-purposes
Version: 0.0.3
Summary: python wrapper for displaypurposes.com's api 
Home-page: https://github.com/KevinRNelson/displaypurposes
Author: Kevin Nelson
Author-email: keronels@ucsc.edu
License: UNKNOWN
Platform: UNKNOWN
Classifier: Programming Language :: Python :: 3
Classifier: License :: OSI Approved :: GNU General Public License v3 or later (GPLv3+)
Classifier: Operating System :: OS Independent
Requires-Python: >=3.6
